python_package_template/__init__.py
python_package_template/py.typed
python_package_template/cli/__init__.py
python_package_template/cli/main.py
python_package_qtemplate-0.1.3.dist-info/LICENSE
python_package_qtemplate-0.1.3.dist-info/METADATA
python_package_qtemplate-0.1.3.dist-info/WHEEL
python_package_qtemplate-0.1.3.dist-info/entry_points.txt
python_package_qtemplate-0.1.3.dist-info/top_level.txt
python_package_qtemplate-0.1.3.dist-info/RECORD
